CHANGELOG.md
sphinxcontrib/cadquery/__init__.py
sphinxcontrib/cadquery/common.py
sphinxcontrib/cadquery/cq_core.py
sphinxcontrib/cadquery/cqgi.py
sphinxcontrib/cadquery/domain.py
sphinxcontrib/cadquery/generate_image.py
sphinxcontrib/cadquery/option_converters.py
sphinxcontrib/cadquery/static/cadquery.css
sphinxcontrib/cadquery/static/dist/vtk-lite.js
sphinxcontrib/cadquery/static/dist/vtk-lite.js.LICENSE.txt
sphinxcontrib/cadquery/static/render.js
sphinxcontrib/cadquery/templates/cadquery-svg.rst.jinja
sphinxcontrib/cadquery/templates/cadquery-vtk.rst.jinja
sphinxcontrib/cadquery/templates/svg-overlay.html.jinja
sphinxcontrib/cadquery/templates/vtk-container.html.jinja
sphinxcontrib_cadquery-0.9.0.dist-info/LICENSE
sphinxcontrib_cadquery-0.9.0.dist-info/LICENSE.vtk-js
sphinxcontrib_cadquery-0.9.0.dist-info/METADATA
sphinxcontrib_cadquery-0.9.0.dist-info/WHEEL
sphinxcontrib_cadquery-0.9.0.dist-info/RECORD
