Metadata-Version: 2.1
Name: sphinxcontrib-cadquery
Version: 0.9.0
Summary: Sphinx extension for rendering CadQuery models.
Home-page: https://github.com/sethfischer/sphinxcontrib-cadquery
License: Apache-2.0
Keywords: cad,cadquery,parametric,programmatic,sphinx,svg,vtk,vtk.js
Author: Seth Fischer
Author-email: seth@fischer.nz
Requires-Python: >=3.9,<3.12
Classifier: Development Status :: 5 - Production/Stable
Classifier: Environment :: Console
Classifier: Environment :: Web Environment
Classifier: Framework :: Sphinx
Classifier: Framework :: Sphinx :: Extension
Classifier: Intended Audience :: Developers
Classifier: Intended Audience :: Science/Research
Classifier: License :: OSI Approved :: Apache Software License
Classifier: Operating System :: POSIX
Classifier: Operating System :: Unix
Classifier: Programming Language :: Python
Classifier: Programming Language :: Python :: 3
Classifier: Programming Language :: Python :: 3.9
Classifier: Programming Language :: Python :: 3.10
Classifier: Programming Language :: Python :: 3.11
Classifier: Programming Language :: Python :: 3 :: Only
Classifier: Topic :: Documentation
Classifier: Topic :: Documentation :: Sphinx
Classifier: Topic :: Scientific/Engineering
Requires-Dist: Sphinx (>=6,<=8)
Requires-Dist: ipython (>=7.31.1)
Requires-Dist: jinja2 (>=3.0)
Project-URL: Bug Tracker, https://github.com/sethfischer/sphinxcontrib-cadquery/issues
Project-URL: Documentation, https://sphinxcontrib-cadquery.readthedocs.io/
Project-URL: Repository, https://github.com/sethfischer/sphinxcontrib-cadquery.git
